cryptol/__init__.py
cryptol/bitvector.py
cryptol/commands.py
cryptol/connection.py
cryptol/cryptoltypes.py
cryptol/custom_fstring.py
cryptol/file_deps.py
cryptol/opaque.py
cryptol/py.typed
cryptol/quoting.py
cryptol/single_connection.py
cryptol/solver.py
cryptol/synchronous.py
cryptol-3.4.0.dist-info/METADATA
cryptol-3.4.0.dist-info/WHEEL
cryptol-3.4.0.dist-info/licenses/LICENSE
cryptol-3.4.0.dist-info/RECORD
