Metadata-Version: 2.4
Name: cryptol
Version: 3.4.0
Summary: Cryptol client for the Cryptol RPC server
License: BSD License
License-File: LICENSE
Keywords: cryptography,verification
Author: Galois, Inc.
Author-email: cryptol-team@galois.com
Requires-Python: >=3.8.0,<4
Classifier: License :: Other/Proprietary License
Classifier: Programming Language :: Python :: 3
Classifier: Programming Language :: Python :: 3.8
Classifier: Programming Language :: Python :: 3.9
Classifier: Programming Language :: Python :: 3.10
Classifier: Programming Language :: Python :: 3.11
Classifier: Programming Language :: Python :: 3.12
Classifier: Programming Language :: Python :: 3.13
Classifier: Programming Language :: Python :: 3.14
Requires-Dist: BitVector (>=3.4.9,<4.0.0)
Requires-Dist: argo-client (>=0.0.14)
Requires-Dist: junit-xml (>=1.9)
Requires-Dist: requests (>=2.31.0)
Requires-Dist: types-requests (>=2.31.0)
Requires-Dist: typing-extensions (>=4.1.1,<5.0.0)
Requires-Dist: urllib3 (>=2.2.0)
